{
  "symbol": "A2b",
  "codeName": "SHINING_REVELRY",
  "displayName": "Shining Revelry",
  "numberOfCards": 111,
  "imageUrl": "shining_revelry.png",
  "packs": [],
  "cards": [
    {
      "number": 1,
      "pokeName": "Weedle",
      "imageUrl": "1-Weedle-Shining-Revelry.jpg",
      "pokeStage": 0,
      "pokeHp": 50,
      "pokeType": "GRASS",
      "pokeWeakness": "FIRE",
      "pokeRetreat": 1,
      "pokeRarity": "D1"
    },
    {
      "number": 2,
      "pokeName": "Kakuna",
      "imageUrl": "2-Kakuna-Shining-Revelry.jpg",
      "pokeStage": 0,
      "pokeEvolvesFrom": "Weedle",
      "pokeHp": 80,
      "pokeType": "GRASS",
      "pokeWeakness": "FIRE",
      "pokeRetreat": 2,
      "pokeRarity": "D2"
    },
    {
      "number": 3,
      "pokeName": "Beedrill ex",
      "imageUrl": "3-Beedrill-ex-Shining-Revelry.jpg",
      "pokeStage": 0,
      "pokeEvolvesFrom": "Kakuna",
      "pokeHp": 170,
      "pokeType": "GRASS",
      "pokeWeakness": "FIRE",
      "pokeRetreat": 1,
      "pokeRarity": "D4"
    },
    {
      "number": 4,
      "pokeName": "Pinsir",
      "imageUrl": "4-Pinsir-Shining-Revelry.jpg",
      "pokeStage": 0,
      "pokeType": "GRASS",
      "pokeWeakness": "FIRE",
      "pokeRetreat": 2,
      "pokeRarity": "D1"
    },
    {
      "number": 5,
      "pokeName": "Sprigatito",
      "imageUrl": "5-Sprigatito-Shining-Revelry.jpg",
      "pokeStage": 0,
      "pokeHp": 60,
      "pokeType": "GRASS",
      "pokeWeakness": "FIRE",
      "pokeRarity": "D1"
    },
    {
      "number": 6,
      "pokeName": "Floragato",
      "imageUrl": "6-Floragato-Shining-Revelry.jpg",
      "pokeStage": 0,
      "pokeType": "GRASS",
      "pokeWeakness": "FIRE",
      "pokeRetreat": 1,
      "pokeRarity": "D2"
    },
    {
      "number": 7,
      "pokeName": "Meowscarada",
      "imageUrl": "7-Meowscarada-Shining-Revelry.jpg",
      "pokeStage": 2,
      "pokeHp": 140,
      "pokeType": "GRASS",
      "pokeWeakness": "FIRE",
      "pokeRetreat": 1,
      "pokeRarity": "D3"
    },
    {
      "number": 8,
      "pokeName": "Charmander",
      "imageUrl": "8-Charmander-Shining-Revelry.jpg",
      "pokeStage": 0,
      "pokeHp": 60,
      "pokeType": "FIRE",
      "pokeWeakness": "WATER",
      "pokeRetreat": 1,
      "pokeRarity": "D1"
    },
    {
      "number": 9,
      "pokeName": "Charmeleon",
      "imageUrl": "9-Charmeleon-Shining-Revelry.jpg",
      "pokeStage": 0,
      "pokeHp": 90,
      "pokeType": "FIRE",
      "pokeWeakness": "WATER",
      "pokeRetreat": 2,
      "pokeRarity": "D2"
    },
    {
      "number": 10,
      "pokeName": "Charizard ex",
      "imageUrl": "10-Charizard-ex-Shining-Revelry.jpg",
      "pokeStage": 2,
      "pokeEvolvesFrom": "Charmeleon",
      "pokeHp": 180,
      "pokeType": "FIRE",
      "pokeWeakness": "WATER",
      "pokeRetreat": 3,
      "pokeRarity": "D4"
    },
    {
      "number": 11,
      "pokeName": "Magmar",
      "imageUrl": "11-Magmar-Shining-Revelry.jpg",
      "pokeStage": 0,
      "pokeHp": 70,
      "pokeType": "FIRE",
      "pokeWeakness": "WATER",
      "pokeRetreat": 1,
      "pokeRarity": "D1"
    },
    {
      "number": 12,
      "pokeName": "Magmortar",
      "imageUrl": "12-Magmortar-Shining-Revelry.jpg",
      "pokeStage": 1,
      "pokeEvolvesFrom": "Magmar",
      "pokeHp": 120,
      "pokeType": "FIRE",
      "pokeWeakness": "WATER",
      "pokeRetreat": 3,
      "pokeRarity": "D3"
    },
    {
      "number": 13,
      "pokeName": "Paldean Tauros",
      "imageUrl": "13-Paldean-Tauros-Shining-Revelry.jpg",
      "pokeStage": 0,
      "pokeHp": 110,
      "pokeType": "FIRE",
      "pokeWeakness": "WATER",
      "pokeRetreat": 2,
      "pokeRarity": "D2"
    },
    {
      "number": 14,
      "pokeName": "Tentacool",
      "imageUrl": "14-Tentacool-Shining-Revelry.jpg",
      "pokeStage": 0,
      "pokeHp": 70,
      "pokeType": "WATER",
      "pokeWeakness": "LIGHTNING",
      "pokeRetreat": 1,
      "pokeRarity": "D1"
    },
    {
      "number": 15,
      "pokeName": "Tentacruel",
      "imageUrl": "15-Tentacruel-Shining-Revelry.jpg",
      "pokeStage": 1,
      "pokeEvolvesFrom": "Tentacool",
      "pokeHp": 100,
      "pokeType": "WATER",
      "pokeWeakness": "LIGHTNING",
      "pokeRetreat": 1,
      "pokeRarity": "D2"
    },
    {
      "number": 16,
      "pokeName": "Buizel",
      "imageUrl": "16-Buizel-Shining-Revelry.jpg",
      "pokeStage": 0,
      "pokeHp": 70,
      "pokeType": "WATER",
      "pokeWeakness": "LIGHTNING",
      "pokeRetreat": 1,
      "pokeRarity": "D1"
    },
    {
      "number": 17,
      "pokeName": "Floatzel",
      "imageUrl": "17-Floatzel-Shining-Revelry.jpg",
      "pokeStage": 1,
      "pokeEvolvesFrom": "Buizel",
      "pokeHp": 90,
      "pokeType": "WATER",
      "pokeWeakness": "LIGHTNING",
      "pokeRetreat": 1,
      "pokeRarity": "D2"
    },
    {
      "number": 18,
      "pokeName": "Wiglett",
      "imageUrl": "18-Wiglett-Shining-Revelry.jpg",
      "pokeStage": 0,
      "pokeHp": 60,
      "pokeType": "WATER",
      "pokeWeakness": "LIGHTNING",
      "pokeRetreat": 1,
      "pokeRarity": "D1"
    },
    {
      "number": 19,
      "pokeName": "Wugtrio ex",
      "imageUrl": "19-Wugtrio-ex-Shining-Revelry.jpg",
      "pokeStage": 1,
      "pokeEvolvesFrom": "Wiglett",
      "pokeHp": 140,
      "pokeType": "WATER",
      "pokeWeakness": "LIGHTNING",
      "pokeRetreat": 1,
      "pokeRarity": "D4"
    },
    {
      "number": 20,
      "pokeName": "Dondozo",
      "imageUrl": "20-Dondozo-Shining-Revelry.jpg",
      "pokeStage": 0,
      "pokeHp": 120,
      "pokeType": "WATER",
      "pokeWeakness": "LIGHTNING",
      "pokeRetreat": 3,
      "pokeRarity": "D3"
    },
    {
      "number": 21,
      "pokeName": "Tatsugiri",
      "imageUrl": "21-Tatsugiri-Shining-Revelry.jpg",
      "pokeStage": 0,
      "pokeHp": 70,
      "pokeType": "WATER",
      "pokeWeakness": "LIGHTNING",
      "pokeRetreat": 1,
      "pokeRarity": "D2"
    },
    {
      "number": 22,
      "pokeName": "Pikachu ex",
      "imageUrl": "22-Pikachu-ex-Shining-Revelry.jpg",
      "pokeStage": 0,
      "pokeHp": 120,
      "pokeType": "LIGHTNING",
      "pokeWeakness": "FIGHTING",
      "pokeRetreat": 1,
      "pokeRarity": "D4"
    },
    {
      "number": 23,
      "pokeName": "Voltorb",
      "imageUrl": "23-Voltorb-Shining-Revelry.jpg",
      "pokeStage": 0,
      "pokeHp": 70,
      "pokeType": "LIGHTNING",
      "pokeWeakness": "FIGHTING",
      "pokeRetreat": 1,
      "pokeRarity": "D1"
    },
    {
      "number": 24,
      "pokeName": "Electrode",
      "imageUrl": "24-Electrode-Shining-Revelry.jpg",
      "pokeStage": 0,
      "pokeHp": 90,
      "pokeType": "LIGHTNING",
      "pokeWeakness": "FIGHTING",
      "pokeRetreat": 1,
      "pokeRarity": "D2"
    },
    {
      "number": 25,
      "pokeName": "Pachirisu",
      "imageUrl": "25-Pachirisu-Shining-Revelry.jpg",
      "pokeStage": 0,
      "pokeHp": 70,
      "pokeType": "LIGHTNING",
      "pokeWeakness": "FIGHTING",
      "pokeRetreat": 1,
      "pokeRarity": "D2"
    },
    {
      "number": 26,
      "pokeName": "Pawmi",
      "imageUrl": "26-Pawmi-Shining-Revelry.jpg",
      "pokeStage": 0,
      "pokeHp": 60,
      "pokeType": "LIGHTNING",
      "pokeWeakness": "FIGHTING",
      "pokeRetreat": 1,
      "pokeRarity": "D1"
    },
    {
      "number": 27,
      "pokeName": "Pawmo",
      "imageUrl": "27-Pawmo-Shining-Revelry.jpg",
      "pokeStage": 1,
      "pokeEvolvesFrom": "Pawmi",
      "pokeHp": 90,
      "pokeType": "LIGHTNING",
      "pokeWeakness": "FIGHTING",
      "pokeRetreat": 1,
      "pokeRarity": "D2"
    },
    {
      "number": 28,
      "pokeName": "Pawmot",
      "imageUrl": "28-Pawmot-Shining-Revelry.jpg",
      "pokeStage": 2,
      "pokeEvolvesFrom": "Pawmo",
      "pokeHp": 140,
      "pokeType": "LIGHTNING",
      "pokeWeakness": "FIGHTING",
      "pokeRetreat": 0,
      "pokeRarity": "D3"
    },
    {
      "number": 29,
      "pokeName": "Abra",
      "imageUrl": "29-Abra-Shining-Revelry.jpg",
      "pokeStage": 0,
      "pokeHp": 60,
      "pokeType": "PSYCHIC",
      "pokeWeakness": "DARKNESS",
      "pokeRetreat": 1,
      "pokeRarity": "D1"
    },
    {
      "number": 30,
      "pokeName": "Kadabra",
      "imageUrl": "30-Kadabra-Shining-Revelry.jpg",
      "pokeStage": 1,
      "pokeEvolvesFrom": "Abra",
      "pokeHp": 80,
      "pokeType": "PSYCHIC",
      "pokeWeakness": "DARKNESS",
      "pokeRetreat": 1,
      "pokeRarity": "D2"
    },
    {
      "number": 31,
      "pokeName": "Alakazam",
      "imageUrl": "31-Alakazam-Shining-Revelry.jpg",
      "pokeStage": 2,
      "pokeEvolvesFrom": "Kadabra",
      "pokeType": "PSYCHIC",
      "pokeWeakness": "DARKNESS",
      "pokeRetreat": 1,
      "pokeRarity": "D3"
    },
    {
      "number": 32,
      "pokeName": "Mr. Mime",
      "imageUrl": "32-Mr_-Mime-Shining-Revelry.jpg",
      "pokeStage": 0,
      "pokeType": "PSYCHIC",
      "pokeWeakness": "DARKNESS",
      "pokeRetreat": 1,
      "pokeRarity": "D1"
    },
    {
      "number": 33,
      "pokeName": "Drifloon",
      "imageUrl": "33-Drifloon-Shining-Revelry.jpg",
      "pokeStage": 0,
      "pokeHp": 60,
      "pokeType": "PSYCHIC",
      "pokeWeakness": "DARKNESS",
      "pokeRetreat": 1,
      "pokeRarity": "D1"
    },
    {
      "number": 34,
      "pokeName": "Drifblim",
      "imageUrl": "34-Drifblim-Shining-Revelry.jpg",
      "pokeStage": 1,
      "pokeEvolvesFrom": "Drifbloom",
      "pokeHp": 90,
      "pokeType": "PSYCHIC",
      "pokeWeakness": "DARKNESS",
      "pokeRetreat": 0,
      "pokeRarity": "D2"
    },
    {
      "number": 35,
      "pokeName": "Giratina ex",
      "imageUrl": "35-Giratina-ex-Shining-Revelry.jpg",
      "pokeStage": 0,
      "pokeHp": 150,
      "pokeType": "PSYCHIC",
      "pokeWeakness": "DARKNESS",
      "pokeRetreat": 2,
      "pokeRarity": "D4"
    },
    {
      "number": 36,
      "pokeName": "Gimmighoul",
      "imageUrl": "36-Gimmighoul-Shining-Revelry.jpg",
      "pokeStage": 0,
      "pokeHp": 60,
      "pokeType": "PSYCHIC",
      "pokeWeakness": "DARKNESS",
      "pokeRetreat": 1,
      "pokeRarity": "D1"
    },
    {
      "number": 37,
      "pokeName": "Machop",
      "imageUrl": "37-Machop-Shining-Revelry.jpg",
      "pokeStage": 0,
      "pokeHp": 60,
      "pokeType": "FIGHTING",
      "pokeWeakness": "PSYCHIC",
      "pokeRetreat": 1,
      "pokeRarity": "D1"
    },
    {
      "number": 38,
      "pokeName": "Machoke",
      "imageUrl": "38-Machoke-Shining-Revelry.jpg",
      "pokeStage": 0,
      "pokeHp": 100,
      "pokeType": "FIGHTING",
      "pokeWeakness": "PSYCHIC",
      "pokeRetreat": 2,
      "pokeRarity": "D1"
    },
    {
      "number": 39,
      "pokeName": "Machamp",
      "imageUrl": "39-Machamp-Shining-Revelry.jpg",
      "pokeStage": 2,
      "pokeEvolvesFrom": "Machoke",
      "pokeHp": 150,
      "pokeType": "FIGHTING",
      "pokeWeakness": "PSYCHIC",
      "pokeRetreat": 2,
      "pokeRarity": "D3"
    },
    {
      "number": 40,
      "pokeName": "Hitmonlee",
      "imageUrl": "40-Hitmonlee-Shining-Revelry.jpg",
      "pokeStage": 0,
      "pokeHp": 80,
      "pokeType": "FIGHTING",
      "pokeWeakness": "PSYCHIC",
      "pokeRetreat": 1,
      "pokeRarity": "D1"
    },
    {
      "number": 41,
      "pokeName": "Hitmonchan",
      "imageUrl": "41-Hitmonchan-Shining-Revelry.jpg",
      "pokeStage": 0,
      "pokeRarity": "UNKNOWN"
    },
    {
      "number": 42,
      "pokeName": "Riolu",
      "imageUrl": "42-Riolu-Shining-Revelry.jpg",
      "pokeStage": 0,
      "pokeRarity": "UNKNOWN"
    },
    {
      "number": 43,
      "pokeName": "Lucario ex",
      "imageUrl": "43-Lucario-ex-Shining-Revelry.jpg",
      "pokeStage": 0,
      "pokeRarity": "UNKNOWN"
    },
    {
      "number": 44,
      "pokeName": "Flamigo",
      "imageUrl": "44-Flamigo-Shining-Revelry.jpg",
      "pokeStage": 0,
      "pokeRarity": "UNKNOWN"
    },
    {
      "number": 45,
      "pokeName": "Ekans",
      "imageUrl": "45-Ekans-Shining-Revelry.jpg",
      "pokeStage": 0,
      "pokeRarity": "UNKNOWN"
    },
    {
      "number": 46,
      "pokeName": "Arbok",
      "imageUrl": "46-Arbok-Shining-Revelry.jpg",
      "pokeStage": 0,
      "pokeRarity": "UNKNOWN"
    },
    {
      "number": 47,
      "pokeName": "Paldean Whooper",
      "imageUrl": "47-Paldean-Whooper-Shining-Revelry.jpg",
      "pokeStage": 0,
      "pokeRarity": "UNKNOWN"
    },
    {
      "number": 48,
      "pokeName": "Paldean Clodsire ex",
      "imageUrl": "48-Paldean-Clodsire-ex-Shining-Revelry.jpg",
      "pokeStage": 0,
      "pokeRarity": "UNKNOWN"
    },
    {
      "number": 49,
      "pokeName": "Spiritomb",
      "imageUrl": "49-Spiritomb-Shining-Revelry.jpg",
      "pokeStage": 0,
      "pokeRarity": "UNKNOWN"
    },
    {
      "number": 50,
      "pokeName": "Shroodle",
      "imageUrl": "50-Shroodle-Shining-Revelry.jpg",
      "pokeStage": 0,
      "pokeRarity": "UNKNOWN"
    },
    {
      "number": 51,
      "pokeName": "Grafaiai",
      "imageUrl": "51-Grafaiai-Shining-Revelry.jpg",
      "pokeStage": 0,
      "pokeRarity": "UNKNOWN"
    },
    {
      "number": 52,
      "pokeName": "Tinkatink",
      "imageUrl": "52-Tinkatink-Shining-Revelry.jpg",
      "pokeStage": 0,
      "pokeRarity": "UNKNOWN"
    },
    {
      "number": 53,
      "pokeName": "Tinkatuff",
      "imageUrl": "53-Tinkatuff-Shining-Revelry.jpg",
      "pokeStage": 0,
      "pokeRarity": "UNKNOWN"
    },
    {
      "number": 54,
      "pokeName": "Tinkaton ex",
      "imageUrl": "54-Tinkaton-ex-Shining-Revelry.jpg",
      "pokeStage": 0,
      "pokeRarity": "UNKNOWN"
    },
    {
      "number": 55,
      "pokeName": "Varoom",
      "imageUrl": "55-Varoom-Shining-Revelry.jpg",
      "pokeStage": 0,
      "pokeRarity": "UNKNOWN"
    },
    {
      "number": 56,
      "pokeName": "Revavroom",
      "imageUrl": "56-Revavroom-Shining-Revelry.jpg",
      "pokeStage": 0,
      "pokeRarity": "UNKNOWN"
    },
    {
      "number": 57,
      "pokeName": "Gholdengo",
      "imageUrl": "57-Gholdengo-Shining-Revelry.jpg",
      "pokeStage": 0,
      "pokeRarity": "UNKNOWN"
    },
    {
      "number": 58,
      "pokeName": "Rattata",
      "imageUrl": "58-Rattata-Shining-Revelry.jpg",
      "pokeStage": 0,
      "pokeRarity": "UNKNOWN"
    },
    {
      "number": 59,
      "pokeName": "Raticate",
      "imageUrl": "59-Raticate-Shining-Revelry.jpg",
      "pokeStage": 0,
      "pokeRarity": "UNKNOWN"
    },
    {
      "number": 60,
      "pokeName": "Jigglypuff",
      "imageUrl": "60-Jigglypuff-Shining-Revelry.jpg",
      "pokeStage": 0,
      "pokeRarity": "UNKNOWN"
    },
    {
      "number": 61,
      "pokeName": "Wigglytuff",
      "imageUrl": "61-Wigglytuff-Shining-Revelry.jpg",
      "pokeStage": 0,
      "pokeRarity": "UNKNOWN"
    },
    {
      "number": 62,
      "pokeName": "Lickitung",
      "imageUrl": "62-Lickitung-Shining-Revelry.jpg",
      "pokeStage": 0,
      "pokeRarity": "UNKNOWN"
    },
    {
      "number": 63,
      "pokeName": "Lickilicky",
      "imageUrl": "63-Lickilicky-Shining-Revelry.jpg",
      "pokeStage": 0,
      "pokeRarity": "UNKNOWN"
    },
    {
      "number": 64,
      "pokeName": "Bidoof",
      "imageUrl": "64-Bidoof-Shining-Revelry.jpg",
      "pokeStage": 0,
      "pokeRarity": "UNKNOWN"
    },
    {
      "number": 65,
      "pokeName": "Bibarel ex",
      "imageUrl": "65-Bibarel-ex-Shining-Revelry.jpg",
      "pokeStage": 0,
      "pokeRarity": "UNKNOWN"
    },
    {
      "number": 66,
      "pokeName": "Buneary",
      "imageUrl": "66-Buneary-Shining-Revelry.jpg",
      "pokeStage": 0,
      "pokeRarity": "UNKNOWN"
    },
    {
      "number": 67,
      "pokeName": "Lopunny",
      "imageUrl": "67-Lopunny-Shining-Revelry.jpg",
      "pokeStage": 0,
      "pokeRarity": "UNKNOWN"
    },
    {
      "number": 68,
      "pokeName": "Cyclizar",
      "imageUrl": "68-Cyclizar-Shining-Revelry.jpg",
      "pokeStage": 0,
      "pokeRarity": "UNKNOWN"
    },
    {
      "number": 69,
      "pokeName": "Iono",
      "imageUrl": "69-Iono-Shining-Revelry.jpg",
      "pokeStage": 0,
      "pokeRarity": "UNKNOWN"
    },
    {
      "number": 70,
      "pokeName": "Pokemon Center Lady",
      "imageUrl": "70-Pokemon-Center-Lady-Shining-Revelry.jpg",
      "pokeStage": 0,
      "pokeRarity": "UNKNOWN"
    },
    {
      "number": 71,
      "pokeName": "Red",
      "imageUrl": "71-Red-Shining-Revelry.jpg",
      "pokeStage": 0,
      "pokeRarity": "UNKNOWN"
    },
    {
      "number": 72,
      "pokeName": "Team Rocket Grunt",
      "imageUrl": "72-Team-Rocket-Grunt-Shining-Revelry.jpg",
      "pokeStage": 0,
      "pokeRarity": "UNKNOWN"
    },
    {
      "number": 73,
      "pokeName": "Meowscarada",
      "imageUrl": "73-Meowscarada-Shining-Revelry.jpg",
      "pokeStage": 0,
      "pokeRarity": "UNKNOWN"
    },
    {
      "number": 74,
      "pokeName": "Buizel",
      "imageUrl": "74-Buizel-Shining-Revelry.jpg",
      "pokeStage": 0,
      "pokeRarity": "UNKNOWN"
    },
    {
      "number": 75,
      "pokeName": "Tatsugiri",
      "imageUrl": "75-Tatsugiri-Shining-Revelry.jpg",
      "pokeStage": 0,
      "pokeRarity": "UNKNOWN"
    },
    {
      "number": 76,
      "pokeName": "Grafaiai",
      "imageUrl": "76-Grafaiai-Shining-Revelry.jpg",
      "pokeStage": 0,
      "pokeRarity": "UNKNOWN"
    },
    {
      "number": 77,
      "pokeName": "Gholdengo",
      "imageUrl": "77-Gholdengo-Shining-Revelry.jpg",
      "pokeStage": 0,
      "pokeRarity": "UNKNOWN"
    },
    {
      "number": 78,
      "pokeName": "Wigglytuff",
      "imageUrl": "78-Wigglytuff-Shining-Revelry.jpg",
      "pokeStage": 0,
      "pokeRarity": "UNKNOWN"
    },
    {
      "number": 79,
      "pokeName": "Beedrill ex",
      "imageUrl": "79-Beedrill-ex-Shining-Revelry.jpg",
      "pokeStage": 0,
      "pokeRarity": "UNKNOWN"
    },
    {
      "number": 80,
      "pokeName": "Charizard ex",
      "imageUrl": "80-Charizard-ex-Shining-Revelry.jpg",
      "pokeStage": 0,
      "pokeRarity": "UNKNOWN"
    },
    {
      "number": 81,
      "pokeName": "Wugtrio ex",
      "imageUrl": "81-Wugtrio-ex-Shining-Revelry.jpg",
      "pokeStage": 0,
      "pokeRarity": "UNKNOWN"
    },
    {
      "number": 82,
      "pokeName": "Pikachu ex",
      "imageUrl": "82-Pikachu-ex-Shining-Revelry.jpg",
      "pokeStage": 0,
      "pokeRarity": "UNKNOWN"
    },
    {
      "number": 83,
      "pokeName": "Giratina ex",
      "imageUrl": "83-Giratina-ex-Shining-Revelry.jpg",
      "pokeStage": 0,
      "pokeRarity": "UNKNOWN"
    },
    {
      "number": 84,
      "pokeName": "Lucario ex",
      "imageUrl": "84-Lucario-ex-Shining-Revelry.jpg",
      "pokeStage": 0,
      "pokeRarity": "UNKNOWN"
    },
    {
      "number": 85,
      "pokeName": "Paldean Clodsire ex",
      "imageUrl": "85-Paldean-Clodsire-ex-Shining-Revelry.jpg",
      "pokeStage": 0,
      "pokeRarity": "UNKNOWN"
    },
    {
      "number": 86,
      "pokeName": "Tinkaton ex",
      "imageUrl": "86-Tinkaton-ex-Shining-Revelry.jpg",
      "pokeStage": 0,
      "pokeRarity": "UNKNOWN"
    },
    {
      "number": 89,
      "pokeName": "Bibarel ex",
      "imageUrl": "89-Bibarel-ex-Shining-Revelry.jpg",
      "pokeStage": 0,
      "pokeRarity": "UNKNOWN"
    },
    {
      "number": 90,
      "pokeName": "Red",
      "imageUrl": "90-Red-Shining-Revelry.jpg",
      "pokeStage": 0,
      "pokeRarity": "UNKNOWN"
    },
    {
      "number": 90,
      "pokeName": "Iono",
      "imageUrl": "90-Iono-Shining-Revelry.jpg",
      "pokeStage": 0,
      "pokeRarity": "UNKNOWN"
    },
    {
      "number": 91,
      "pokeName": "Team Rocket Grunt",
      "imageUrl": "91-Team-Rocket-Grunt-Shining-Revelry.jpg",
      "pokeStage": 0,
      "pokeRarity": "UNKNOWN"
    },
    {
      "number": 91,
      "pokeName": "Pokemon Center Lady",
      "imageUrl": "91-Pokemon-Center-Lady-Shining-Revelry.jpg",
      "pokeStage": 0,
      "pokeRarity": "UNKNOWN"
    },
    {
      "number": 92,
      "pokeName": "Pikachu ex",
      "imageUrl": "92-Pikachu-ex-Shining-Revelry.jpg",
      "pokeStage": 0,
      "pokeRarity": "UNKNOWN"
    },
    {
      "number": 93,
      "pokeName": "Paldean Clodsire ex",
      "imageUrl": "93-Paldean-Clodsire-ex-Shining-Revelry.jpg",
      "pokeStage": 0,
      "pokeRarity": "UNKNOWN"
    },
    {
      "number": 94,
      "pokeName": "Tinkaton ex",
      "imageUrl": "94-Tinkaton-ex-Shining-Revelry.jpg",
      "pokeStage": 0,
      "pokeRarity": "UNKNOWN"
    },
    {
      "number": 95,
      "pokeName": "Bibarel ex",
      "imageUrl": "95-Bibarel-ex-Shining-Revelry.jpg",
      "pokeStage": 0,
      "pokeRarity": "UNKNOWN"
    },
    {
      "number": 96,
      "pokeName": "Giratina ex",
      "imageUrl": "96-Giratina-ex-Shining-Revelry.jpg",
      "pokeStage": 0,
      "pokeRarity": "UNKNOWN"
    },
    {
      "number": 97,
      "pokeName": "Weedle",
      "imageUrl": "97-Weedle-Shining-Revelry.jpg",
      "pokeStage": 0,
      "pokeRarity": "SHINY1"
    },
    {
      "number": 98,
      "pokeName": "Kakuna",
      "imageUrl": "98-Kakuna-Shining-Revelry.jpg",
      "pokeStage": 0,
      "pokeRarity": "SHINY1"
    },
    {
      "number": 99,
      "pokeName": "Charmander",
      "imageUrl": "99-Charmander-Shining-Revelry.jpg",
      "pokeStage": 0,
      "pokeRarity": "SHINY1"
    },
    {
      "number": 100,
      "pokeName": "Charmeleon",
      "imageUrl": "100-Charmeleon-Shining-Revelry.jpg",
      "pokeStage": 0,
      "pokeRarity": "SHINY1"
    },
    {
      "number": 101,
      "pokeName": "Wiglett",
      "imageUrl": "101-Wiglett-Shining-Revelry.jpg",
      "pokeStage": 0,
      "pokeRarity": "SHINY1"
    },
    {
      "number": 102,
      "pokeName": "Dondozo",
      "imageUrl": "102-Dondozo-Shining-Revelry.jpg",
      "pokeStage": 0,
      "pokeRarity": "SHINY1"
    },
    {
      "number": 103,
      "pokeName": "Pachirisu",
      "imageUrl": "103-Pachirisu-Shining-Revelry.jpg",
      "pokeStage": 0,
      "pokeRarity": "SHINY1"
    },
    {
      "number": 104,
      "pokeName": "Riolu",
      "imageUrl": "104-Riolu-Shining-Revelry.jpg",
      "pokeStage": 0,
      "pokeRarity": "SHINY1"
    },
    {
      "number": 105,
      "pokeName": "Varoom",
      "imageUrl": "105-Varoom-Shining-Revelry.jpg",
      "pokeStage": 0,
      "pokeRarity": "SHINY1"
    },
    {
      "number": 106,
      "pokeName": "Revavroom",
      "imageUrl": "106-Revavroom-Shining-Revelry.jpg",
      "pokeStage": 0,
      "pokeRarity": "SHINY1"
    },
    {
      "number": 107,
      "pokeName": "Beedrill ex",
      "imageUrl": "107-Beedrill-ex-Shining-Revelry.jpg",
      "pokeStage": 0,
      "pokeRarity": "SHINY2"
    },
    {
      "number": 108,
      "pokeName": "Charizard ex",
      "imageUrl": "108-Charizard-ex-Shining-Revelry.jpg",
      "pokeStage": 0,
      "pokeRarity": "SHINY2"
    },
    {
      "number": 109,
      "pokeName": "Wugtrio ex",
      "imageUrl": "109-Wugtrio-ex-Shining-Revelry.jpg",
      "pokeStage": 0,
      "pokeRarity": "SHINY2"
    },
    {
      "number": 110,
      "pokeName": "Lucario ex",
      "imageUrl": "110-Lucario-ex-Shining-Revelry.jpg",
      "pokeStage": 0,
      "pokeRarity": "SHINY2"
    },
    {
      "number": 111,
      "pokeName": "Poke ball",
      "imageUrl": "111-Poke-ball-Shining-Revelry.jpg",
      "pokeStage": 0,
      "pokeRarity": "C"
    }
  ]
}